nudantic/__init__.py
nudantic-0.1.3.dist-info/METADATA
nudantic-0.1.3.dist-info/WHEEL
nudantic-0.1.3.dist-info/top_level.txt
nudantic-0.1.3.dist-info/RECORD
