Metadata-Version: 2.1
Name: nudantic
Version: 0.1.3
Summary: Numpy Array type compatible with Pydantic
Author-email: Marcel Claramunt <marcel@moveread.com>
Project-URL: repo, https://github.com/marciclabas/tbd.git
Requires-Python: >=3.10
Requires-Dist: numpy
Requires-Dist: pydantic-core
